websense/__init__.py
websense/cleaner.py
websense/cli.py
websense/fetcher.py
websense/parser.py
websense/scraper.py
websense/searcher.py
websense-0.4.1.dist-info/licenses/LICENSE
websense-0.4.1.dist-info/METADATA
websense-0.4.1.dist-info/WHEEL
websense-0.4.1.dist-info/entry_points.txt
websense-0.4.1.dist-info/top_level.txt
websense-0.4.1.dist-info/RECORD
