Metadata-Version: 2.4
Name: websense
Version: 0.4.1
Summary: A modular AI-powered web scraper for data pipelines.
Author-email: Ahmet Ataşoğlu <ahmetatasoglu98@gmail.com>
License: MIT
Project-URL: Homepage, https://github.com/atasoglu/websense
Keywords: scraper,web,automation,data-extraction,parsing,crawler,ai,llm,machine-learning
Classifier: Programming Language :: Python :: 3
Classifier: License :: OSI Approved :: MIT License
Classifier: Operating System :: OS Independent
Requires-Python: >=3.10
License-File: LICENSE
Requires-Dist: requests
Requires-Dist: beautifulsoup4
Requires-Dist: ask2api
Requires-Dist: markdownify
Requires-Dist: rich-click
Requires-Dist: ddgs
Provides-Extra: dev
Requires-Dist: pre-commit; extra == "dev"
Requires-Dist: pytest; extra == "dev"
Requires-Dist: pytest-cov; extra == "dev"
Dynamic: license-file
